{
    "AWSTemplateFormatVersion": "2010-09-09",
    "Description": "Lambda permissions for Function URL public access (Partner Central MCP)",
    "Resources": {
        "InvokeFunctionUrlPermission": {
            "Type": "AWS::Lambda::Permission",
            "Properties": {
                "Action": "lambda:InvokeFunctionUrl",
                "FunctionName": "partner-central-mcp-proxy",
                "FunctionUrlAuthType": "NONE",
                "Principal": "*"
            }
        },
        "InvokeFunctionPermission": {
            "Type": "AWS::Lambda::Permission",
            "Properties": {
                "Action": "lambda:InvokeFunction",
                "FunctionName": "partner-central-mcp-proxy",
                "InvokedViaFunctionUrl": true,
                "Principal": "*"
            }
        }
    }
}
